digiflow/__init__.py
digiflow/common.py
digiflow/digiflow_export.py
digiflow/digiflow_generate.py
digiflow/digiflow_identifier.py
digiflow/digiflow_io.py
digiflow/digiflow_metadata.py
digiflow/digiflow_multisaf.py
digiflow/record/__init__.py
digiflow/record/common.py
digiflow/record/record_criteria.py
digiflow/record/record_handler.py
digiflow/record/record_service.py
digiflow/resources/digilife.ini
digiflow/resources/xsd/alto-4-2.xsd
digiflow/resources/xsd/mets-1-12.xsd
digiflow/resources/xsd/mix-2-0.xsd
digiflow/resources/xsd/mods-3-7.xsd
digiflow/resources/xsd/mods-3-8.xsd
digiflow/resources/xsd/xlink.xsd
digiflow/resources/xsd/xml.xsd
digiflow/resources/xsl/ddb_validierung_mets-mods-ap-digitalisierte-medien.xsl
digiflow/resources/xsl/ddb_validierung_mets-mods-ap-digitalisierte-zeitungen.xsl
digiflow/validate/__init__.py
digiflow/validate/common.py
digiflow/validate/fsdata.py
digiflow/validate/imgdata.py
digiflow/validate/metadata_ddb.py
digiflow/validate/metadata_xsd.py
digiflow/validate/metadata_xslt.py
digiflow-6.6.18.dist-info/licenses/LICENCE
digiflow-6.6.18.dist-info/METADATA
digiflow-6.6.18.dist-info/WHEEL
digiflow-6.6.18.dist-info/top_level.txt
digiflow-6.6.18.dist-info/RECORD
