Metadata-Version: 2.4
Name: digiflow
Version: 6.6.18
Summary: Father's Little Digitization Workflow Helper
Author-email: Universitäts- und Landesbibliothek Sachsen-Anhalt <development@bibliothek.uni-halle.de>
Project-URL: Homepage, https://github.com/ulb-sachsen-anhalt/digital-flow
Classifier: Intended Audience :: Developers
Classifier: Intended Audience :: Education
Classifier: Development Status :: 6 - Mature
Classifier: Programming Language :: Python :: 3
Classifier: License :: OSI Approved :: MIT License
Requires-Python: >=3.8
License-File: LICENCE
Requires-Dist: lxml
Requires-Dist: Pillow
Requires-Dist: numpy
Requires-Dist: docker
Requires-Dist: requests
Requires-Dist: saxonche
Requires-Dist: openpyxl
Dynamic: license-file
